DiscordFuncs/Bot.py
DiscordFuncs/Webhook.py
DiscordFuncs/__init__.py
DiscordFuncs-1.0.0.dist-info/METADATA
DiscordFuncs-1.0.0.dist-info/WHEEL
DiscordFuncs-1.0.0.dist-info/top_level.txt
DiscordFuncs-1.0.0.dist-info/RECORD
