Metadata-Version: 2.1
Name: DiscordFuncs
Version: 1.0.0
Summary: Some small discord.py functions for bot developers!
Home-page: https://github.com/AstroOrbis/DiscordFuncs
Author: Astro Orbis
Author-email: astroorbis@gmail.com
License: UNKNOWN
Keywords: python3,discord,discord bot,discord webhook
Platform: UNKNOWN
Classifier: Programming Language :: Python :: 3
Classifier: License :: OSI Approved :: MIT License
Classifier: Operating System :: OS Independent
Requires-Python: >=3.6
Requires-Dist: discord
Requires-Dist: requests
Requires-Dist: aiohttp
Requires-Dist: discord-webhook
